image_transforms-0.0.2.dist-info/METADATA
image_transforms-0.0.2.dist-info/WHEEL
image_transforms-0.0.2.dist-info/licenses/LICENSE
imgtfs/__init__.py
imgtfs/base.py
imgtfs/gray.py
image_transforms-0.0.2.dist-info/RECORD
