Metadata-Version: 2.1
Name: image_transforms
Version: 0.0.2
Summary: simple image transformations
Author-Email: TaoChenyue <chenyue.Tao@qq.com>
License: MIT
Requires-Python: <3.12,>=3.10
Requires-Dist: pillow>=10.3.0
Requires-Dist: opencv-python>=4.9.0.80
Requires-Dist: opencv-python-headless>=4.9.0.80
